{
  "openapi": "3.0.1",
  "info": {
    "title": "ReadBookApi",
    "version": "1.0"
  },
  "paths": {
    "/Home/all": {
      "get": {
        "tags": [
          "Home"
        ],
        "responses": {
          "200": {
            "description": "OK",
            "content": {
              "text/plain": {
                "schema": {
                  "type": "array",
                  "items": { }
                }
              },
              "application/json": {
                "schema": {
                  "type": "array",
                  "items": { }
                }
              },
              "text/json": {
                "schema": {
                  "type": "array",
                  "items": { }
                }
              }
            }
          }
        }
      }
    }
  },
  "components": { }
}